__init__.py
max_heap_tree.py
maxheapq_snow/__init__.py
maxheapq_snow/max_heap.py
maxheapq_snow-0.0.2.dist-info/LICENSE
maxheapq_snow-0.0.2.dist-info/METADATA
maxheapq_snow-0.0.2.dist-info/WHEEL
maxheapq_snow-0.0.2.dist-info/top_level.txt
maxheapq_snow-0.0.2.dist-info/RECORD
