Metadata-Version: 2.2
Name: maxheapq_snow
Version: 0.0.2
Summary: Max binary heap module, similar to heapq
Author-email: snow Avocado <nikhilreddymara@gmail.com>
Project-URL: Homepage, https://github.com/snowAvocado/maxheapq
Project-URL: Issues, https://github.com/snowAvocado/maxheapq/issues
Classifier: Programming Language :: Python :: 3
Classifier: License :: OSI Approved :: MIT License
Classifier: Operating System :: OS Independent
Requires-Python: >=3.10.12
License-File: LICENSE
